bma_client_lib/__init__.py
bma_client_lib/bma_client.py
bma_client_lib/datastructures.py
bma_client_lib/pillow_resize_and_crop.py
bma_client_lib/tests/__init__.py
bma_client_lib/tests/test_pillow_resize_and_crop.py
bma_client_lib-0.12.0.dist-info/licenses/LICENSE
bma_client_lib-0.12.0.dist-info/METADATA
bma_client_lib-0.12.0.dist-info/WHEEL
bma_client_lib-0.12.0.dist-info/top_level.txt
bma_client_lib-0.12.0.dist-info/RECORD
