Metadata-Version: 2.4
Name: bma-client-lib
Version: 0.12.0
Summary: BornHack Media Archive Client Library
Author: Thomas Steen Rasmussen
Author-email: thomas@gibfest.dk
Project-URL: homepage, https://github.com/bornhack/bma-client-lib-python
Classifier: Programming Language :: Python :: 3
Classifier: Operating System :: OS Independent
Requires-Python: >=3.11
License-File: LICENSE
Requires-Dist: exifread==3.0.0
Requires-Dist: ffmpeg-python==0.2.0
Requires-Dist: httpx==0.27.2
Requires-Dist: opencv-python==4.10.0.84
Requires-Dist: pillow==11.0.0
Requires-Dist: python-magic==0.4.27
Requires-Dist: PyMuPDF==1.25.1
Provides-Extra: dev
Requires-Dist: pre-commit==4.0.0; extra == "dev"
Requires-Dist: setuptools-scm==8.0.4; extra == "dev"
Provides-Extra: test
Requires-Dist: pytest==8.3.3; extra == "test"
Requires-Dist: pytest-mock==3.14.0; extra == "test"
Dynamic: license-file
